{
  "series_id": "2812763",
  "title": "cs2",
  "data_model_version": "3.45",
  "format": "best-of-1",
  "started": true,
  "finished": true,
  "valid": true,
  "started_at": "2025-06-13T15:44:21.975Z",
  "updated_at": "2025-06-13T16:26:41.887Z",
  "duration": "PT42M19.912S",
  "winning_team_id": "51822",
  "map_count": 1,
  "round_count": 17,
  "teams": [
    {
      "team_id": "50074",
      "name": "AURORA",
      "score": 0,
      "won": false,
      "kills": 48,
      "deaths": 60,
      "assists": 13,
      "assists_received": 13,
      "headshots": 24,
      "players": [
        {
          "player_id": "76561197967432889",
          "name": "MAJ3R",
          "participation_status": "active",
          "kills": 4,
          "deaths": 13,
          "assists": 4,
          "assists_received": 1,
          "headshots": 2
        },
        {
          "player_id": "76561198044118796",
          "name": "XANTARES",
          "participation_status": "active",
          "kills": 9,
          "deaths": 10,
          "assists": 2,
          "assists_received": 2,
          "headshots": 4
        },
        {
          "player_id": "76561198083485506",
          "name": "woxic",
          "participation_status": "active",
          "kills": 8,
          "deaths": 13,
          "assists": 2,
          "assists_received": 2,
          "headshots": 4
        },
        {
          "player_id": "76561198410750263",
          "name": "jottAAA",
          "participation_status": "active",
          "kills": 19,
          "deaths": 10,
          "assists": 1,
          "assists_received": 6,
          "headshots": 10
        },
        {
          "player_id": "76561198812513923",
          "name": "Wicadia",
          "participation_status": "active",
          "kills": 8,
          "deaths": 14,
          "assists": 4,
          "assists_received": 2,
          "headshots": 4
        }
      ],
      "original_team_id": "50074"
    },
    {
      "team_id": "51822",
      "name": "G2 Esports",
      "score": 1,
      "won": true,
      "kills": 60,
      "deaths": 48,
      "assists": 18,
      "assists_received": 18,
      "headshots": 34,
      "players": [
        {
          "player_id": "76561197982141573",
          "name": "snax",
          "participation_status": "active",
          "kills": 8,
          "deaths": 10,
          "assists": 5,
          "assists_received": 2,
          "headshots": 4
        },
        {
          "player_id": "76561198012872053",
          "name": "huNter",
          "participation_status": "active",
          "kills": 18,
          "deaths": 9,
          "assists": 7,
          "assists_received": 6,
          "headshots": 12
        },
        {
          "player_id": "76561198050922008",
          "name": "hades",
          "participation_status": "active",
          "kills": 12,
          "deaths": 8,
          "assists": 1,
          "assists_received": 6,
          "headshots": 2
        },
        {
          "player_id": "76561198068002993",
          "name": "HeavyGoD",
          "participation_status": "active",
          "kills": 12,
          "deaths": 11,
          "assists": 2,
          "assists_received": 3,
          "headshots": 7
        },
        {
          "player_id": "76561198080703143",
          "name": "malbsMd",
          "participation_status": "active",
          "kills": 10,
          "deaths": 10,
          "assists": 3,
          "assists_received": 1,
          "headshots": 9
        }
      ],
      "original_team_id": "51822"
    }
  ],
  "games": [
    {
      "game_id": "2fd97f09-6b61-4b42-944b-8fa479b14fb7",
      "sequence_number": 1,
      "map_id": "c8b5d99d-5739-32ab-a49a-ff1e0f367b29",
      "map_name": "inferno",
      "started": true,
      "finished": true,
      "started_at": "2025-06-13T15:44:26.040Z",
      "duration": "PT42M15.847S",
      "round_count": 17,
      "winning_team_id": "51822",
      "teams": [
        {
          "team_id": "50074",
          "name": "AURORA",
          "score": 4,
          "won": false,
          "kills": 48,
          "deaths": 60,
          "assists": 13,
          "headshots": 24,
          "damage_dealt": 5539,
          "damage_taken": 6322,
          "team_adr": 325.82,
          "players": [
            {
              "player_id": "76561197967432889",
              "name": "MAJ3R",
              "participation_status": "active",
              "kills": 4,
              "deaths": 13,
              "assists": 4,
              "assists_received": 1,
              "headshots": 2,
              "damage_dealt": 792,
              "damage_taken": 1300,
              "kd_ratio": 0.308,
              "adr": 46.59,
              "kills_per_round": 0.235,
              "deaths_per_round": 0.765,
              "assists_per_round": 0.235,
              "headshot_percentage": 50.0
            },
            {
              "player_id": "76561198044118796",
              "name": "XANTARES",
              "participation_status": "active",
              "kills": 9,
              "deaths": 10,
              "assists": 2,
              "assists_received": 2,
              "headshots": 4,
              "damage_dealt": 1104,
              "damage_taken": 1098,
              "kd_ratio": 0.9,
              "adr": 64.94,
              "kills_per_round": 0.529,
              "deaths_per_round": 0.588,
              "assists_per_round": 0.118,
              "headshot_percentage": 44.44
            },
            {
              "player_id": "76561198083485506",
              "name": "woxic",
              "participation_status": "active",
              "kills": 8,
              "deaths": 13,
              "assists": 2,
              "assists_received": 2,
              "headshots": 4,
              "damage_dealt": 897,
              "damage_taken": 1300,
              "kd_ratio": 0.615,
              "adr": 52.76,
              "kills_per_round": 0.471,
              "deaths_per_round": 0.765,
              "assists_per_round": 0.118,
              "headshot_percentage": 50.0
            },
            {
              "player_id": "76561198410750263",
              "name": "jottAAA",
              "participation_status": "active",
              "kills": 19,
              "deaths": 10,
              "assists": 1,
              "assists_received": 6,
              "headshots": 10,
              "damage_dealt": 1737,
              "damage_taken": 1167,
              "kd_ratio": 1.9,
              "adr": 102.18,
              "kills_per_round": 1.118,
              "deaths_per_round": 0.588,
              "assists_per_round": 0.059,
              "headshot_percentage": 52.63
            },
            {
              "player_id": "76561198812513923",
              "name": "Wicadia",
              "participation_status": "active",
              "kills": 8,
              "deaths": 14,
              "assists": 4,
              "assists_received": 2,
              "headshots": 4,
              "damage_dealt": 1009,
              "damage_taken": 1457,
              "kd_ratio": 0.571,
              "adr": 59.35,
              "kills_per_round": 0.471,
              "deaths_per_round": 0.824,
              "assists_per_round": 0.235,
              "headshot_percentage": 50.0
            }
          ],
          "original_team_id": "50074"
        },
        {
          "team_id": "51822",
          "name": "G2 Esports",
          "score": 13,
          "won": true,
          "kills": 60,
          "deaths": 48,
          "assists": 18,
          "headshots": 34,
          "damage_dealt": 6322,
          "damage_taken": 5539,
          "team_adr": 371.88,
          "players": [
            {
              "player_id": "76561197982141573",
              "name": "snax",
              "participation_status": "active",
              "kills": 8,
              "deaths": 10,
              "assists": 5,
              "assists_received": 2,
              "headshots": 4,
              "damage_dealt": 1019,
              "damage_taken": 1056,
              "kd_ratio": 0.8,
              "adr": 59.94,
              "kills_per_round": 0.471,
              "deaths_per_round": 0.588,
              "assists_per_round": 0.294,
              "headshot_percentage": 50.0
            },
            {
              "player_id": "76561198012872053",
              "name": "huNter",
              "participation_status": "active",
              "kills": 18,
              "deaths": 9,
              "assists": 7,
              "assists_received": 6,
              "headshots": 12,
              "damage_dealt": 1919,
              "damage_taken": 1052,
              "kd_ratio": 2.0,
              "adr": 112.88,
              "kills_per_round": 1.059,
              "deaths_per_round": 0.529,
              "assists_per_round": 0.412,
              "headshot_percentage": 66.67
            },
            {
              "player_id": "76561198050922008",
              "name": "hades",
              "participation_status": "active",
              "kills": 12,
              "deaths": 8,
              "assists": 1,
              "assists_received": 6,
              "headshots": 2,
              "damage_dealt": 876,
              "damage_taken": 987,
              "kd_ratio": 1.5,
              "adr": 51.53,
              "kills_per_round": 0.706,
              "deaths_per_round": 0.471,
              "assists_per_round": 0.059,
              "headshot_percentage": 16.67
            },
            {
              "player_id": "76561198068002993",
              "name": "HeavyGoD",
              "participation_status": "active",
              "kills": 12,
              "deaths": 11,
              "assists": 2,
              "assists_received": 3,
              "headshots": 7,
              "damage_dealt": 1219,
              "damage_taken": 1284,
              "kd_ratio": 1.091,
              "adr": 71.71,
              "kills_per_round": 0.706,
              "deaths_per_round": 0.647,
              "assists_per_round": 0.118,
              "headshot_percentage": 58.33
            },
            {
              "player_id": "76561198080703143",
              "name": "malbsMd",
              "participation_status": "active",
              "kills": 10,
              "deaths": 10,
              "assists": 3,
              "assists_received": 1,
              "headshots": 9,
              "damage_dealt": 1289,
              "damage_taken": 1160,
              "kd_ratio": 1.0,
              "adr": 75.82,
              "kills_per_round": 0.588,
              "deaths_per_round": 0.588,
              "assists_per_round": 0.176,
              "headshot_percentage": 90.0
            }
          ],
          "original_team_id": "51822"
        }
      ]
    }
  ],
  "scheduled_start": "2025-06-13T15:45:00Z",
  "stage": "stage_3",
  "stage_display_name": "Stage 3",
  "scheduled_team_names": [
    "AURORA",
    "G2 Esports"
  ],
  "scheduled_format": "Bo1",
  "included_in_major": true,
  "exclusion_reason": null
}