{
  "series_id": "2814375",
  "title": "cs2",
  "data_model_version": "3.45",
  "format": "best-of-1",
  "started": true,
  "finished": true,
  "valid": true,
  "started_at": "2025-06-07T15:16:13.928Z",
  "updated_at": "2025-06-07T15:50:48.531Z",
  "duration": "PT34M34.603S",
  "winning_team_id": "51885",
  "map_count": 1,
  "round_count": 2,
  "teams": [
    {
      "team_id": "51967",
      "name": "Falcons",
      "score": 0,
      "won": false,
      "kills": 4,
      "deaths": 15,
      "assists": 2,
      "assists_received": 2,
      "headshots": 1,
      "players": [
        {
          "player_id": "76561197983956651",
          "name": "Magisk",
          "participation_status": "active",
          "kills": 0,
          "deaths": 2,
          "assists": 1,
          "assists_received": 0,
          "headshots": 0
        },
        {
          "player_id": "76561197996678278",
          "name": "TeSeS",
          "participation_status": "active",
          "kills": 0,
          "deaths": 2,
          "assists": 1,
          "assists_received": 0,
          "headshots": 0
        },
        {
          "player_id": "76561198041683378",
          "name": "NiKo",
          "participation_status": "active",
          "kills": 1,
          "deaths": 2,
          "assists": 0,
          "assists_received": 1,
          "headshots": 0
        },
        {
          "player_id": "76561198057282432",
          "name": "kyxsan",
          "participation_status": "active",
          "kills": 2,
          "deaths": 2,
          "assists": 0,
          "assists_received": 1,
          "headshots": 0
        },
        {
          "player_id": "76561198074762801",
          "name": "m0NESY",
          "participation_status": "active",
          "kills": 0,
          "deaths": 2,
          "assists": 0,
          "assists_received": 0,
          "headshots": 0
        },
        {
          "player_id": "76561198073117127",
          "name": "nicoodoz",
          "participation_status": "active",
          "kills": 0,
          "deaths": 1,
          "assists": 0,
          "assists_received": 0,
          "headshots": 0
        },
        {
          "player_id": "76561198079183361",
          "name": "spooke",
          "participation_status": "active",
          "kills": 1,
          "deaths": 1,
          "assists": 0,
          "assists_received": 0,
          "headshots": 1
        },
        {
          "player_id": "76561198248953762",
          "name": "Buzz",
          "participation_status": "active",
          "kills": 0,
          "deaths": 1,
          "assists": 0,
          "assists_received": 0,
          "headshots": 0
        },
        {
          "player_id": "76561198252434500",
          "name": "F1KU",
          "participation_status": "active",
          "kills": 0,
          "deaths": 1,
          "assists": 0,
          "assists_received": 0,
          "headshots": 0
        },
        {
          "player_id": "76561198292598811",
          "name": "Chr1zN",
          "participation_status": "active",
          "kills": 0,
          "deaths": 1,
          "assists": 0,
          "assists_received": 0,
          "headshots": 0
        }
      ],
      "original_team_id": "51967"
    },
    {
      "team_id": "51885",
      "name": "B8",
      "score": 1,
      "won": true,
      "kills": 15,
      "deaths": 4,
      "assists": 4,
      "assists_received": 4,
      "headshots": 9,
      "players": [
        {
          "player_id": "76561198304115519",
          "name": "alex666",
          "participation_status": "active",
          "kills": 1,
          "deaths": 2,
          "assists": 2,
          "assists_received": 0,
          "headshots": 0
        },
        {
          "player_id": "76561198305036904",
          "name": "npl",
          "participation_status": "active",
          "kills": 2,
          "deaths": 0,
          "assists": 1,
          "assists_received": 1,
          "headshots": 2
        },
        {
          "player_id": "76561198359519930",
          "name": "headtr1ck",
          "participation_status": "active",
          "kills": 2,
          "deaths": 0,
          "assists": 0,
          "assists_received": 0,
          "headshots": 0
        },
        {
          "player_id": "76561198382173659",
          "name": "kensizor",
          "participation_status": "active",
          "kills": 2,
          "deaths": 0,
          "assists": 0,
          "assists_received": 0,
          "headshots": 2
        },
        {
          "player_id": "76561199149812353",
          "name": "esenthial",
          "participation_status": "active",
          "kills": 3,
          "deaths": 1,
          "assists": 0,
          "assists_received": 2,
          "headshots": 1
        },
        {
          "player_id": "76561197995817501",
          "name": "FL1T",
          "participation_status": "active",
          "kills": 0,
          "deaths": 0,
          "assists": 0,
          "assists_received": 0,
          "headshots": 0
        },
        {
          "player_id": "76561198014259134",
          "name": "FL4MUS",
          "participation_status": "active",
          "kills": 0,
          "deaths": 1,
          "assists": 0,
          "assists_received": 0,
          "headshots": 0
        },
        {
          "player_id": "76561198044045107",
          "name": "electroNic",
          "participation_status": "active",
          "kills": 3,
          "deaths": 0,
          "assists": 0,
          "assists_received": 1,
          "headshots": 2
        },
        {
          "player_id": "76561198055109028",
          "name": "ICY",
          "participation_status": "active",
          "kills": 0,
          "deaths": 0,
          "assists": 1,
          "assists_received": 0,
          "headshots": 0
        },
        {
          "player_id": "76561198080114546",
          "name": "fame",
          "participation_status": "active",
          "kills": 2,
          "deaths": 0,
          "assists": 0,
          "assists_received": 0,
          "headshots": 2
        }
      ],
      "original_team_id": "51885"
    }
  ],
  "games": [
    {
      "game_id": "39fbabc5-d3f4-4490-9f76-6fe041b7ca1b",
      "sequence_number": 1,
      "map_id": "c8b5d99d-5739-32ab-a49a-ff1e0f367b29",
      "map_name": "inferno",
      "started": true,
      "finished": true,
      "started_at": "2025-06-07T15:47:45.964Z",
      "duration": "PT3M2.567S",
      "round_count": 2,
      "winning_team_id": "51885",
      "teams": [
        {
          "team_id": "51967",
          "name": "Falcons",
          "score": 0,
          "won": false,
          "kills": 4,
          "deaths": 15,
          "assists": 2,
          "headshots": 1,
          "damage_dealt": 865,
          "damage_taken": 2499,
          "team_adr": 432.5,
          "players": [
            {
              "player_id": "76561197983956651",
              "name": "Magisk",
              "participation_status": "active",
              "kills": 0,
              "deaths": 2,
              "assists": 1,
              "assists_received": 0,
              "headshots": 0,
              "damage_dealt": 76,
              "damage_taken": 261,
              "kd_ratio": 0.0,
              "adr": 38.0,
              "kills_per_round": 0.0,
              "deaths_per_round": 1.0,
              "assists_per_round": 0.5,
              "headshot_percentage": 0.0
            },
            {
              "player_id": "76561197996678278",
              "name": "TeSeS",
              "participation_status": "active",
              "kills": 0,
              "deaths": 2,
              "assists": 1,
              "assists_received": 0,
              "headshots": 0,
              "damage_dealt": 111,
              "damage_taken": 324,
              "kd_ratio": 0.0,
              "adr": 55.5,
              "kills_per_round": 0.0,
              "deaths_per_round": 1.0,
              "assists_per_round": 0.5,
              "headshot_percentage": 0.0
            },
            {
              "player_id": "76561198041683378",
              "name": "NiKo",
              "participation_status": "active",
              "kills": 1,
              "deaths": 2,
              "assists": 0,
              "assists_received": 1,
              "headshots": 0,
              "damage_dealt": 44,
              "damage_taken": 625,
              "kd_ratio": 0.5,
              "adr": 22.0,
              "kills_per_round": 0.5,
              "deaths_per_round": 1.0,
              "assists_per_round": 0.0,
              "headshot_percentage": 0.0
            },
            {
              "player_id": "76561198057282432",
              "name": "kyxsan",
              "participation_status": "active",
              "kills": 2,
              "deaths": 2,
              "assists": 0,
              "assists_received": 1,
              "headshots": 0,
              "damage_dealt": 274,
              "damage_taken": 343,
              "kd_ratio": 1.0,
              "adr": 137.0,
              "kills_per_round": 1.0,
              "deaths_per_round": 1.0,
              "assists_per_round": 0.0,
              "headshot_percentage": 0.0
            },
            {
              "player_id": "76561198074762801",
              "name": "m0NESY",
              "participation_status": "active",
              "kills": 0,
              "deaths": 2,
              "assists": 0,
              "assists_received": 0,
              "headshots": 0,
              "damage_dealt": 23,
              "damage_taken": 411,
              "kd_ratio": 0.0,
              "adr": 11.5,
              "kills_per_round": 0.0,
              "deaths_per_round": 1.0,
              "assists_per_round": 0.0,
              "headshot_percentage": 0.0
            },
            {
              "player_id": "76561198073117127",
              "name": "nicoodoz",
              "participation_status": "active",
              "kills": 0,
              "deaths": 1,
              "assists": 0,
              "assists_received": 0,
              "headshots": 0,
              "damage_dealt": 11,
              "damage_taken": 100,
              "kd_ratio": 0.0,
              "adr": 5.5,
              "kills_per_round": 0.0,
              "deaths_per_round": 0.5,
              "assists_per_round": 0.0,
              "headshot_percentage": 0.0
            },
            {
              "player_id": "76561198079183361",
              "name": "spooke",
              "participation_status": "active",
              "kills": 1,
              "deaths": 1,
              "assists": 0,
              "assists_received": 0,
              "headshots": 1,
              "damage_dealt": 291,
              "damage_taken": 135,
              "kd_ratio": 1.0,
              "adr": 145.5,
              "kills_per_round": 0.5,
              "deaths_per_round": 0.5,
              "assists_per_round": 0.0,
              "headshot_percentage": 100.0
            },
            {
              "player_id": "76561198248953762",
              "name": "Buzz",
              "participation_status": "active",
              "kills": 0,
              "deaths": 1,
              "assists": 0,
              "assists_received": 0,
              "headshots": 0,
              "damage_dealt": 24,
              "damage_taken": 100,
              "kd_ratio": 0.0,
              "adr": 12.0,
              "kills_per_round": 0.0,
              "deaths_per_round": 0.5,
              "assists_per_round": 0.0,
              "headshot_percentage": 0.0
            },
            {
              "player_id": "76561198252434500",
              "name": "F1KU",
              "participation_status": "active",
              "kills": 0,
              "deaths": 1,
              "assists": 0,
              "assists_received": 0,
              "headshots": 0,
              "damage_dealt": 0,
              "damage_taken": 100,
              "kd_ratio": 0.0,
              "adr": 0.0,
              "kills_per_round": 0.0,
              "deaths_per_round": 0.5,
              "assists_per_round": 0.0,
              "headshot_percentage": 0.0
            },
            {
              "player_id": "76561198292598811",
              "name": "Chr1zN",
              "participation_status": "active",
              "kills": 0,
              "deaths": 1,
              "assists": 0,
              "assists_received": 0,
              "headshots": 0,
              "damage_dealt": 11,
              "damage_taken": 100,
              "kd_ratio": 0.0,
              "adr": 5.5,
              "kills_per_round": 0.0,
              "deaths_per_round": 0.5,
              "assists_per_round": 0.0,
              "headshot_percentage": 0.0
            }
          ],
          "original_team_id": "51967"
        },
        {
          "team_id": "51885",
          "name": "B8",
          "score": 3,
          "won": true,
          "kills": 15,
          "deaths": 4,
          "assists": 4,
          "headshots": 9,
          "damage_dealt": 2499,
          "damage_taken": 865,
          "team_adr": 1249.5,
          "players": [
            {
              "player_id": "76561198304115519",
              "name": "alex666",
              "participation_status": "active",
              "kills": 1,
              "deaths": 2,
              "assists": 2,
              "assists_received": 0,
              "headshots": 0,
              "damage_dealt": 399,
              "damage_taken": 304,
              "kd_ratio": 0.5,
              "adr": 199.5,
              "kills_per_round": 0.5,
              "deaths_per_round": 1.0,
              "assists_per_round": 1.0,
              "headshot_percentage": 0.0
            },
            {
              "player_id": "76561198305036904",
              "name": "npl",
              "participation_status": "active",
              "kills": 2,
              "deaths": 0,
              "assists": 1,
              "assists_received": 1,
              "headshots": 2,
              "damage_dealt": 673,
              "damage_taken": 23,
              "kd_ratio": 0.0,
              "adr": 336.5,
              "kills_per_round": 1.0,
              "deaths_per_round": 0.0,
              "assists_per_round": 0.5,
              "headshot_percentage": 100.0
            },
            {
              "player_id": "76561198359519930",
              "name": "headtr1ck",
              "participation_status": "active",
              "kills": 2,
              "deaths": 0,
              "assists": 0,
              "assists_received": 0,
              "headshots": 0,
              "damage_dealt": 159,
              "damage_taken": 81,
              "kd_ratio": 0.0,
              "adr": 79.5,
              "kills_per_round": 1.0,
              "deaths_per_round": 0.0,
              "assists_per_round": 0.0,
              "headshot_percentage": 0.0
            },
            {
              "player_id": "76561198382173659",
              "name": "kensizor",
              "participation_status": "active",
              "kills": 2,
              "deaths": 0,
              "assists": 0,
              "assists_received": 0,
              "headshots": 2,
              "damage_dealt": 199,
              "damage_taken": 0,
              "kd_ratio": 0.0,
              "adr": 99.5,
              "kills_per_round": 1.0,
              "deaths_per_round": 0.0,
              "assists_per_round": 0.0,
              "headshot_percentage": 100.0
            },
            {
              "player_id": "76561199149812353",
              "name": "esenthial",
              "participation_status": "active",
              "kills": 3,
              "deaths": 1,
              "assists": 0,
              "assists_received": 2,
              "headshots": 1,
              "damage_dealt": 534,
              "damage_taken": 120,
              "kd_ratio": 3.0,
              "adr": 267.0,
              "kills_per_round": 1.5,
              "deaths_per_round": 0.5,
              "assists_per_round": 0.0,
              "headshot_percentage": 33.33
            },
            {
              "player_id": "76561197995817501",
              "name": "FL1T",
              "participation_status": "active",
              "kills": 0,
              "deaths": 0,
              "assists": 0,
              "assists_received": 0,
              "headshots": 0,
              "damage_dealt": 0,
              "damage_taken": 53,
              "kd_ratio": 0.0,
              "adr": 0.0,
              "kills_per_round": 0.0,
              "deaths_per_round": 0.0,
              "assists_per_round": 0.0,
              "headshot_percentage": 0.0
            },
            {
              "player_id": "76561198014259134",
              "name": "FL4MUS",
              "participation_status": "active",
              "kills": 0,
              "deaths": 1,
              "assists": 0,
              "assists_received": 0,
              "headshots": 0,
              "damage_dealt": 0,
              "damage_taken": 100,
              "kd_ratio": 0.0,
              "adr": 0.0,
              "kills_per_round": 0.0,
              "deaths_per_round": 0.5,
              "assists_per_round": 0.0,
              "headshot_percentage": 0.0
            },
            {
              "player_id": "76561198044045107",
              "name": "electroNic",
              "participation_status": "active",
              "kills": 3,
              "deaths": 0,
              "assists": 0,
              "assists_received": 1,
              "headshots": 2,
              "damage_dealt": 282,
              "damage_taken": 127,
              "kd_ratio": 0.0,
              "adr": 141.0,
              "kills_per_round": 1.5,
              "deaths_per_round": 0.0,
              "assists_per_round": 0.0,
              "headshot_percentage": 66.67
            },
            {
              "player_id": "76561198055109028",
              "name": "ICY",
              "participation_status": "active",
              "kills": 0,
              "deaths": 0,
              "assists": 1,
              "assists_received": 0,
              "headshots": 0,
              "damage_dealt": 53,
              "damage_taken": 0,
              "kd_ratio": 0.0,
              "adr": 26.5,
              "kills_per_round": 0.0,
              "deaths_per_round": 0.0,
              "assists_per_round": 0.5,
              "headshot_percentage": 0.0
            },
            {
              "player_id": "76561198080114546",
              "name": "fame",
              "participation_status": "active",
              "kills": 2,
              "deaths": 0,
              "assists": 0,
              "assists_received": 0,
              "headshots": 2,
              "damage_dealt": 200,
              "damage_taken": 57,
              "kd_ratio": 0.0,
              "adr": 100.0,
              "kills_per_round": 1.0,
              "deaths_per_round": 0.0,
              "assists_per_round": 0.0,
              "headshot_percentage": 100.0
            }
          ],
          "original_team_id": "51885"
        }
      ]
    }
  ],
  "scheduled_start": "2025-06-07T15:10:00Z",
  "stage": "stage_2",
  "stage_display_name": "Stage 2",
  "scheduled_team_names": [
    "Team Falcons",
    "B8"
  ],
  "scheduled_format": "Bo1",
  "included_in_major": true,
  "exclusion_reason": null
}